ccachesim.so
cachesim/__init__.py
cachesim/backend.c
cachesim/backend.so
cachesim/cache.py
pycachesim-0.1.2.2.dist-info/DESCRIPTION.rst
pycachesim-0.1.2.2.dist-info/entry_points.txt
pycachesim-0.1.2.2.dist-info/METADATA
pycachesim-0.1.2.2.dist-info/metadata.json
pycachesim-0.1.2.2.dist-info/RECORD
pycachesim-0.1.2.2.dist-info/top_level.txt
pycachesim-0.1.2.2.dist-info/WHEEL
