Metadata-Version: 2.0
Name: pycachesim
Version: 0.1.2.2
Summary: Python Cache Hierarchy Simulator
Home-page: https://github.com/cod3monk/pycachesim
Author: Julian Hammer
Author-email: julian.hammer@fau.de
License: AGPLv3
Keywords: hpc performance benchmark analysis
Platform: UNKNOWN
Classifier: Development Status :: 3 - Alpha
Classifier: Intended Audience :: Developers
Classifier: Intended Audience :: Science/Research
Classifier: Topic :: Scientific/Engineering
Classifier: Topic :: Software Development
Classifier: Topic :: Utilities
Classifier: License :: OSI Approved :: GNU Affero General Public License v3
Classifier: Programming Language :: Python :: 2
Classifier: Programming Language :: Python :: 2.7
Classifier: Programming Language :: Python :: 3
Classifier: Programming Language :: Python :: 3.4
